{"schema":"","start":1752694149117,"finish":1752694178031,"outcome":"COMPLETED","remoteAddress":"10.140.82.181:49848","id":"17880279-af17-f234-249d-8fab7ad1de3f","query":"select \n\tnation, \n\to_year, \n\tsum(amount) as sum_profit \nfrom \n\t( \n\t\tselect \n\t\t\tnation.n_name as nation, \n\t\t\textract(year from orders.o_orderdate) as o_year, \n\t\t\tlineitem.l_extendedprice * (1 - lineitem.l_discount) - partsupp.ps_supplycost * lineitem.l_quantity as amount \n\t\tfrom \n\t\t\tdfs.`tmp/part.parquet` part, \n\t\t\tdfs.`tmp/supplier.parquet` supplier, \n\t\t\tdfs.`tmp/lineitem.parquet` lineitem, \n\t\t\tdfs.`tmp/partsupp.parquet` partsupp, \n\t\t\tdfs.`tmp/orders.parquet` orders, \n\t\t\tdfs.`tmp/nation.parquet` nation \n\t\twhere \n\t\t\tsupplier.s_suppkey = lineitem.l_suppkey \n\t\t\tand partsupp.ps_suppkey = lineitem.l_suppkey \n\t\t\tand partsupp.ps_partkey = lineitem.l_partkey \n\t\t\tand part.p_partkey = lineitem.l_partkey \n\t\t\tand orders.o_orderkey = lineitem.l_orderkey \n\t\t\tand supplier.s_nationkey = nation.n_nationkey \n\t\t\tand part.p_name like '%green%' \n\t) as profit \ngroup by \n\tnation, \n\to_year \norder by \n\tnation, \n\to_year desc","user":"anonymous"}
